fauxgen-0.3.1.data/scripts/fauxgen
fauxgen-0.3.1.dist-info/METADATA
fauxgen-0.3.1.dist-info/WHEEL
fauxgen/__init__.py
fauxgen/generator.py
fauxgen/py.typed
fauxgen/unset.py
fauxgen-0.3.1.dist-info/RECORD
