Metadata-Version: 2.4
Name: fauxgen
Version: 0.3.1
Summary: Add your description here
Author-email: Hironori Yamamoto <mr.nikoru918@gmail.com>
Requires-Python: >=3.10
